<?xml version="1.0" encoding="UTF-8"?>

<newsitem date="1996-11-14" id="root" itemid="50553" xml:lang="pt">
<title></title>
<headline> ACÇÕES SEGUEM MISTAS,S/GRANDES OSCILAÇÕES ATÉ FECHO. </headline>
<byline></byline>
<dateline></dateline>
<text>
<p> As acções do Contínuo seguiam mistas na meia sessão e a liquidez no cash a somar 3,2 milhões de contos, destacando-se os negócios com Engil-SGPS, Portucel Industrial (PI) e Portugal Telecom (PT), não se prevendo fortes alterações até ao fecho, depois de Nova Iorque registar pequenas oscilações no índice. Futuros sobre o PSI20 negoceiam 241 contratos. *Índice PSI-20 (.PSI20)cai 0,20 pct para 4.885,06 pontos *Futuro PSI20 Nov96 (PSI20Z6)cai p/ 4.880 vs 4.889 pontos *PI sobe 3 escudos para 932. Negociadas 184.120 *PT cai 5 escudos para 4.160. Negociadas 159.805 (segue comentário de mercado). </p>
<p> (c) Reuters Limited 1996. </p></text>
<copyright>(c) Reuters Limited 1996</copyright>
<metadata>
<codes class="bip:countries:1.0">
<code code="YVgvGvkGBy">
<editdetail action="confirmed" attribution="Reuters BIP Coding Group" date="1996-11-14"></editdetail></code>
<code code="NdSwuLBHiK">
<editdetail action="confirmed" attribution="Reuters BIP Coding Group" date="1996-11-14"></editdetail></code>
<code code="CdumMPPVob">
<editdetail action="confirmed" attribution="Reuters BIP Coding Group" date="1996-11-14"></editdetail></code></codes>
<codes class="bip:topics:1.0">
<code code="XRKsjZXhVZ">
<editdetail action="confirmed" attribution="Reuters BIP Coding Group" date="1996-11-14"></editdetail></code>
<code code="oBrxnxcGIt">
<editdetail action="confirmed" attribution="Reuters BIP Coding Group" date="1996-11-14"></editdetail></code></codes>
<dc element="dc.publisher" value="Reuters Holdings Plc"></dc>
<dc element="dc.datepublished" value="1996-11-14"></dc>
<dc element="dc.source" value="Reuters - Notícias em Português"></dc>
<dc element="dc.creator.location" value=""></dc>
<dc element="dc.creator.location.country.name" value=""></dc></metadata></newsitem>