<?xml version="1.0" encoding="UTF-8"?>

<newsitem date="1997-05-26" id="root" itemid="54962" xml:lang="pt">
<title></title>
<headline> Resumo transacções no mercado Contínuo - (PDNX). </headline>
<byline></byline>
<dateline></dateline>
<text>
<p> LISBOA, 26 Mai (Reuter) - Transacções no Contínuo (números </p>
<p> da sessão anterior entre parentesis): (MC=milhões de contos). </p>
<p>         Quantidade     Valor </p>
<p> Mercado Contínuo Acções 1.100.419(1.845.547) 3,091 MC( 7,160 MC) </p>
<p>        OT  752.233(  696.597) 7,343 MC( 8,006 MC) Futuros OT-10       826( 720) 8,982 MC( 7,849 MC) Futuros PSI20     1.489(    1.703) 0,989 MC( 1,123 MC) Índices  Oficial BVL (.BVLG)     1.494,72    + 0,36 pct     BVL30  (.BVL30)    2.850,99    + 0,37 pct     PSI-20 (.PSI20)    6.620,52    + 0,45 pct     ORF(TRM 5,9557 vs 5,9185 pct)   112,90    - 0,11 pct     FPI (Fincor Privatisation)    1.299,25    + 0,13 pct     ----Lisboa Editorial,351.1.3113121. </p>
<p> (c) Reuters Limited 1997. </p></text>
<copyright>(c) Reuters Limited 1997</copyright>
<metadata>
<codes class="bip:countries:1.0">
<code code="kzNqaFaBjp">
<editdetail action="confirmed" attribution="Reuters BIP Coding Group" date="1997-05-26"></editdetail></code>
<code code="VTkhOLBaFi">
<editdetail action="confirmed" attribution="Reuters BIP Coding Group" date="1997-05-26"></editdetail></code>
<code code="LwTqgiIjPR">
<editdetail action="confirmed" attribution="Reuters BIP Coding Group" date="1997-05-26"></editdetail></code></codes>
<codes class="bip:topics:1.0">
<code code="loLTJPCugd">
<editdetail action="confirmed" attribution="Reuters BIP Coding Group" date="1997-05-26"></editdetail></code>
<code code="SvEtOnfZYr">
<editdetail action="confirmed" attribution="Reuters BIP Coding Group" date="1997-05-26"></editdetail></code></codes>
<dc element="dc.publisher" value="Reuters Holdings Plc"></dc>
<dc element="dc.datepublished" value="1997-05-26"></dc>
<dc element="dc.source" value="Reuters - Notícias em Português"></dc>
<dc element="dc.creator.location" value=""></dc>
<dc element="dc.creator.location.country.name" value=""></dc></metadata></newsitem>