<?xml version="1.0" encoding="UTF-8"?>

<newsitem date="1997-01-31" id="root" itemid="52265" xml:lang="pt">
<title></title>
<headline> NEGÓCIOS BOLSA LISBOA AUMENTAM 90 VEZES EM 10 ANOS. </headline>
<byline></byline>
<dateline></dateline>
<text>
<p> LISBOA, 31 Jan (Reuter) - O volume de transacções da Bolsa de Valores de Lisboa (BVL) aumentou mais de 90 vezes nos últimos 10 anos para fechar o ano de 1996 com 3.389 milhões de contos (MC) negociados, refere um documento da BVL. </p>
<p> Em 1986, a BVL transaccionou 36 MC durante 196 sessões. Nos últimos 10 anos da praça lisboeta, o ano mais &apos;rentável&apos; foi 1994, com o volume de negócios a somar mais de 3.800 MC. </p>
<p> Tendo como base o ano de 1988, o índice BVL Geral (.BVLG) registou um crescimento de perto de 200 pct em oito anos. </p>
<p> A capitalização bolsista atingiu, em 1996, 10.646 MC contra 690 MC em 1986. </p>
<p> - Paula Cordeiro, Lisboa Editorial, 351-1-3113125. </p>
<p> (c) Reuters Limited 1997. </p></text>
<copyright>(c) Reuters Limited 1997</copyright>
<metadata>
<codes class="bip:countries:1.0">
<code code="tUHtVeCxPS">
<editdetail action="confirmed" attribution="Reuters BIP Coding Group" date="1997-01-31"></editdetail></code>
<code code="PQOzIjScRc">
<editdetail action="confirmed" attribution="Reuters BIP Coding Group" date="1997-01-31"></editdetail></code>
<code code="yUwlobVwHE">
<editdetail action="confirmed" attribution="Reuters BIP Coding Group" date="1997-01-31"></editdetail></code></codes>
<codes class="bip:topics:1.0">
<code code="oYbOAXUqbW">
<editdetail action="confirmed" attribution="Reuters BIP Coding Group" date="1997-01-31"></editdetail></code>
<code code="KnKzfhJjsB">
<editdetail action="confirmed" attribution="Reuters BIP Coding Group" date="1997-01-31"></editdetail></code></codes>
<dc element="dc.publisher" value="Reuters Holdings Plc"></dc>
<dc element="dc.datepublished" value="1997-01-31"></dc>
<dc element="dc.source" value="Reuters - Notícias em Português"></dc>
<dc element="dc.creator.location" value=""></dc>
<dc element="dc.creator.location.country.name" value=""></dc></metadata></newsitem>