<?xml version="1.0" encoding="UTF-8"?>

<newsitem date="1997-06-20" id="root" itemid="55595" xml:lang="pt">
<title></title>
<headline> Escudo fecha estável vs marco em sessão apática. </headline>
<byline></byline>
<dateline></dateline>
<text>
<p> LISBOA, 20 Jun (Reuter) - O escudo fechou calmo e estável contra o marco, numa sessão apática e sem muitos interesses, continunado a sua evolução condicionada pelo rumo que o dólar vier a tomar. </p>
<p> Às 1620 TMG, o escudo cotava 100,83/86 por marco, o mesmo nível da abertura, contra 100,785 na cotação indicativa do Banco de Portugal (BP). </p>
<p> &quot;As moedas europeias estão paradas contra o marco e o escudo não foge à regra, aguardando que o dólar se decida se é para quebrar consolidadamente os 1,73 marcos ou se é para ir para baixo&quot;, disse um operador. </p>
<p>     ----Lisboa Editorial, 351.1.3113121. </p>
<p> (c) Reuters Limited 1997. </p></text>
<copyright>(c) Reuters Limited 1997</copyright>
<metadata>
<codes class="bip:countries:1.0">
<code code="HlHqPtcMHu">
<editdetail action="confirmed" attribution="Reuters BIP Coding Group" date="1997-06-20"></editdetail></code>
<code code="OmJFBUeEDz">
<editdetail action="confirmed" attribution="Reuters BIP Coding Group" date="1997-06-20"></editdetail></code>
<code code="HDxSvhdTFr">
<editdetail action="confirmed" attribution="Reuters BIP Coding Group" date="1997-06-20"></editdetail></code></codes>
<codes class="bip:topics:1.0">
<code code="AhZjynweQR">
<editdetail action="confirmed" attribution="Reuters BIP Coding Group" date="1997-06-20"></editdetail></code>
<code code="JuhZLLkTyI">
<editdetail action="confirmed" attribution="Reuters BIP Coding Group" date="1997-06-20"></editdetail></code>
<code code="bCEZmzJeZm">
<editdetail action="confirmed" attribution="Reuters BIP Coding Group" date="1997-06-20"></editdetail></code></codes>
<dc element="dc.publisher" value="Reuters Holdings Plc"></dc>
<dc element="dc.datepublished" value="1997-06-20"></dc>
<dc element="dc.source" value="Reuters - Notícias em Português"></dc>
<dc element="dc.creator.location" value=""></dc>
<dc element="dc.creator.location.country.name" value=""></dc></metadata></newsitem>