<?xml version="1.0" encoding="UTF-8"?>

<newsitem date="1996-11-20" id="root" itemid="50675" xml:lang="pt">
<title></title>
<headline> RESUMO TRANSACÇÕES NO MERCADO CONTÍNUO - (PDNX). </headline>
<byline></byline>
<dateline></dateline>
<text>
<p>     LISBOA, 19 Nov (Reuter) - Transacções no Contínuo (números </p>
<p> da sessão anterior entre parentesis): (MC=milhões de contos). </p>
<p>         Quantidade     Valor </p>
<p> Mercado Contínuo Acções 4.446.841(3.099.571) 7,031 MC( 6,088 MC) </p>
<p>        OT     1.584.434(1.683.124)18,194 MC(16,811 MC) Futuros OT-10     2.058(    2.058)21,777 MC(21,777 MC) Futuros PSI20       941( 941) 0,469 MC( 0,469 MC) Índices  Oficial BVL (.BVLG)     1.122,42    + 0,04 pct     BVL30  (.BVL30)    2.079,89    + 0,14 pct     PSI-20 (.PSI20)    4.953,23    + 0,19 pct     ORF(TRM 6,8256 vs 6,8108 pct)   110,10    - 0,05 pct     FPI (Fincor Privatisation)    1.131,13    - 0,27 pct     ----Lisboa Editorial,1.1.3113121. </p>
<p> (c) Reuters Limited 1996. </p></text>
<copyright>(c) Reuters Limited 1996</copyright>
<metadata>
<codes class="bip:countries:1.0">
<code code="UzcJjSNJvz">
<editdetail action="confirmed" attribution="Reuters BIP Coding Group" date="1996-11-20"></editdetail></code>
<code code="XhhSitoCdv">
<editdetail action="confirmed" attribution="Reuters BIP Coding Group" date="1996-11-20"></editdetail></code>
<code code="wLkJasJBSj">
<editdetail action="confirmed" attribution="Reuters BIP Coding Group" date="1996-11-20"></editdetail></code></codes>
<codes class="bip:topics:1.0">
<code code="fWnLZTQZCi">
<editdetail action="confirmed" attribution="Reuters BIP Coding Group" date="1996-11-20"></editdetail></code>
<code code="LOSSjuBzvK">
<editdetail action="confirmed" attribution="Reuters BIP Coding Group" date="1996-11-20"></editdetail></code></codes>
<dc element="dc.publisher" value="Reuters Holdings Plc"></dc>
<dc element="dc.datepublished" value="1996-11-20"></dc>
<dc element="dc.source" value="Reuters - Notícias em Português"></dc>
<dc element="dc.creator.location" value=""></dc>
<dc element="dc.creator.location.country.name" value=""></dc></metadata></newsitem>